{
  "home_visit_about": {
    "canonical": {
      "handle": "homepage",
      "title": "WTF | Welcome To Florida - Cape Coral's Premier Kava Bar & Wellness Destination",
      "id": "gid://shopify/Page/112710811826",
      "score": 199.86666666666667
    },
    "duplicates": [
      {
        "handle": "contact",
        "title": "Visit WTF",
        "id": "gid://shopify/Page/101784813746"
      },
      {
        "handle": "about-us",
        "title": "About Us",
        "id": "gid://shopify/Page/108040454322"
      },
      {
        "handle": "about-wtf-welcome-to-florida",
        "title": "About WTF | Welcome To Florida",
        "id": "gid://shopify/Page/112707961010"
      },
      {
        "handle": "our-story",
        "title": "Our Story",
        "id": "gid://shopify/Page/108871581874"
      },
      {
        "handle": "visit-cape-coral-kava-bar",
        "title": "Visit Our Cape Coral Kava Bar Today | WTF Welcome To Florida",
        "id": "gid://shopify/Page/112706814130"
      },
      {
        "handle": "home",
        "title": "Home",
        "id": "gid://shopify/Page/108871745714"
      },
      {
        "handle": "about-cape-coral-kava-bar",
        "title": "About WTF | Welcome To Florida - Cape Coral Kava Bar",
        "id": "gid://shopify/Page/112706158770"
      },
      {
        "handle": "take-home-items",
        "title": "Take Home Items",
        "id": "gid://shopify/Page/113479680178"
      }
    ],
    "redirect_count": 8
  },
  "kava_bar_near_me": {
    "canonical": {
      "handle": "kava-bars-near-me",
      "title": "Kava Bars Near Me | Cape Coral & Southwest Florida | WTF Welcome To Florida",
      "id": "gid://shopify/Page/112708747442",
      "score": 143.76666666666665
    },
    "duplicates": [
      {
        "handle": "cape-coral-kava-bar",
        "title": "Cape Coral Kava Bar | WTF Welcome To Florida | Premium Kava & Kratom",
        "id": "gid://shopify/Page/112708681906"
      },
      {
        "handle": "wtf-is-a-kava-bar-florida-guide",
        "title": "WTF is a Kava Bar? Florida's Ultimate Guide to Kava, Kratom, & THC Drinks",
        "id": "gid://shopify/Page/113187618994"
      },
      {
        "handle": "southwest-florida-kava-bar",
        "title": "Southwest Florida Kava Bar | Fort Myers & Cape Coral | WTF Welcome To Florida",
        "id": "gid://shopify/Page/112708714674"
      },
      {
        "handle": "kava-bar-cape-coral-fl",
        "title": "Kava Bar Cape Coral FL - Premium Kava & Kratom | WTF Florida",
        "id": "gid://shopify/Page/112706224306"
      }
    ],
    "redirect_count": 4
  },
  "education_hubs": {
    "canonical": {
      "handle": "natural-wellness-guide",
      "title": "Natural Wellness Guide | Kava, Kratom & Hemp Education",
      "id": "gid://shopify/Page/112707993778",
      "score": 138.06666666666666
    },
    "duplicates": [
      {
        "handle": "education",
        "title": "Education",
        "id": "gid://shopify/Page/113124409522"
      }
    ],
    "redirect_count": 1
  },
  "blog_guides": {
    "canonical": {
      "handle": "thc-drinks-near-me",
      "title": "THC Drinks Near Me: The Florida Guide to Elevated, Alcohol-Free Vibes",
      "id": "gid://shopify/Page/115101139122",
      "score": 184.4
    },
    "duplicates": [
      {
        "handle": "blog",
        "title": "WTF Blog",
        "id": "gid://shopify/Page/114291671218"
      },
      {
        "handle": "wtfs-infused-drinks",
        "title": "WTF's Infused Drinks",
        "id": "gid://shopify/Page/108095242418"
      },
      {
        "handle": "alcohol-free-date-ideas-cape-coral",
        "title": "5 Alcohol-Free Date Ideas in Cape Coral",
        "id": "gid://shopify/Page/114291802290"
      },
      {
        "handle": "kava-vs-kratom-comparison",
        "title": "Kava vs Kratom: How These Two Botanicals Compare",
        "id": "gid://shopify/Page/114291769522"
      },
      {
        "handle": "what-is-kava-beginners-guide",
        "title": "What is Kava? A Beginner's Guide to the South Pacific's Relaxation Root",
        "id": "gid://shopify/Page/114291703986"
      },
      {
        "handle": "what-is-kratom-florida-botanical",
        "title": "What is Kratom? Exploring Florida's Favorite Brewed Botanical",
        "id": "gid://shopify/Page/114291736754"
      }
    ],
    "redirect_count": 6
  },
  "social_landers": {
    "canonical": {
      "handle": "wtf-landing-snapchat",
      "title": "wtf-landing-google",
      "id": "gid://shopify/Page/109029228722",
      "score": 184.46666666666667
    },
    "duplicates": [
      {
        "handle": "wtf-landing-youtube",
        "title": "wtf-landing-youtube",
        "id": "gid://shopify/Page/109029294258"
      },
      {
        "handle": "wtf-landing-facebook",
        "title": "wtf-landing-facebook",
        "id": "gid://shopify/Page/109029163186"
      },
      {
        "handle": "wtf-landing-snapchat-1",
        "title": "wtf-landing-snapchat",
        "id": "gid://shopify/Page/109029261490"
      },
      {
        "handle": "wtf-landing-tiktok",
        "title": "wtf-landing-tiktok",
        "id": "gid://shopify/Page/109029195954"
      }
    ],
    "redirect_count": 4
  },
  "operational": {
    "canonical": {
      "handle": "wtf-landing",
      "title": "landing-page",
      "id": "gid://shopify/Page/109028704434",
      "score": 193.96666666666667
    },
    "duplicates": [
      {
        "handle": "admin-dashboard",
        "title": "Admin Dashboard",
        "id": "gid://shopify/Page/113124442290"
      },
      {
        "handle": "site-map",
        "title": "Site Map | WTF Welcome To Florida | Find Everything",
        "id": "gid://shopify/Page/112708944050"
      },
      {
        "handle": "order-online-cape-coral-pickup",
        "title": "Order Online for Cape Coral Pickup | WTF Welcome To Florida",
        "id": "gid://shopify/Page/112706846898"
      },
      {
        "handle": "data-sharing-opt-out",
        "title": "Your privacy choices",
        "id": "gid://shopify/Page/101784846514"
      },
      {
        "handle": "cart-test",
        "title": "Cart Test",
        "id": "gid://shopify/Page/113514152114"
      },
      {
        "handle": "mobile-ordering",
        "title": "Mobile Ordering",
        "id": "gid://shopify/Page/113123197106"
      }
    ],
    "redirect_count": 6
  },
  "uncategorized": {
    "canonical": {
      "handle": "faq",
      "title": "FAQ",
      "id": "gid://shopify/Page/113181687986",
      "score": 205.2
    },
    "duplicates": [
      {
        "handle": "google-landing",
        "title": "Google Landing - WTF Welcome To Florida",
        "id": "gid://shopify/Page/112741941426"
      },
      {
        "handle": "facebook-landing",
        "title": "Facebook Landing - WTF Welcome To Florida",
        "id": "gid://shopify/Page/112741154994"
      },
      {
        "handle": "tiktok-landing",
        "title": "TikTok Landing - WTF Welcome To Florida",
        "id": "gid://shopify/Page/112741875890"
      },
      {
        "handle": "youtube-landing",
        "title": "YouTube Landing - WTF Welcome To Florida",
        "id": "gid://shopify/Page/112741908658"
      },
      {
        "handle": "snapchat-landing",
        "title": "Snapchat Landing - WTF Welcome To Florida",
        "id": "gid://shopify/Page/112741843122"
      },
      {
        "handle": "wtf-infusion-lounge",
        "title": "Explore Our Functional Beverages",
        "id": "gid://shopify/Page/110013939890"
      },
      {
        "handle": "drink-menu",
        "title": "Drink-In Menu",
        "id": "gid://shopify/Page/113039114418"
      },
      {
        "handle": "wtf-experience-cape-coral",
        "title": "The WTF Experience | Cape Coral's Premier Kava & Wellness Destination",
        "id": "gid://shopify/Page/112708026546"
      },
      {
        "handle": "drinks",
        "title": "Drinks",
        "id": "gid://shopify/Page/113124343986"
      },
      {
        "handle": "cape-coral-events",
        "title": "Cape Coral Events - Live Music & Paint Nights | WTF Florida",
        "id": "gid://shopify/Page/112706191538"
      },
      {
        "handle": "thc-shots",
        "title": "THC Shots",
        "id": "gid://shopify/Page/113479581874"
      },
      {
        "handle": "fun-stuff",
        "title": "Fun Stuff",
        "id": "gid://shopify/Page/113479647410"
      },
      {
        "handle": "thc-drinks",
        "title": "THC Drinks",
        "id": "gid://shopify/Page/113479516338"
      },
      {
        "handle": "dry-goods",
        "title": "Dry Goods",
        "id": "gid://shopify/Page/113124376754"
      },
      {
        "handle": "kratom-teas",
        "title": "Kratom Teas",
        "id": "gid://shopify/Page/113479188658"
      },
      {
        "handle": "kava-drinks",
        "title": "Kava Drinks",
        "id": "gid://shopify/Page/113479483570"
      },
      {
        "handle": "draft-pours",
        "title": "Draft Pours",
        "id": "gid://shopify/Page/113479549106"
      },
      {
        "handle": "canned-drinks",
        "title": "Canned Drinks",
        "id": "gid://shopify/Page/113479614642"
      }
    ],
    "redirect_count": 18
  }
}